[
  {
    "Category": {
      "CategoryID": 1,
      "CategoryName": "Beverages",
      "Description": "Soft drinks, coffees, teas, beers, and ales"
    },
    "ProductID": 38,
    "ProductName": "Côte de Blaye",
    "Cost": 263.5,
    "Stock": 17,
    "Discontinued": false,
    "CategoryID": 1
  },
  {
    "Category": {
      "CategoryID": 3,
      "CategoryName": "Confections",
      "Description": "Desserts, candies, and sweet breads"
    },
    "ProductID": 20,
    "ProductName": "Sir Rodney's Marmalade",
    "Cost": 81.0,
    "Stock": 40,
    "Discontinued": false,
    "CategoryID": 3
  },
  {
    "Category": {
      "CategoryID": 8,
      "CategoryName": "Seafood",
      "Description": "Seaweed and fish"
    },
    "ProductID": 18,
    "ProductName": "Carnarvon Tigers",
    "Cost": 62.5,
    "Stock": 42,
    "Discontinued": false,
    "CategoryID": 8
  },
  {
    "Category": {
      "CategoryID": 4,
      "CategoryName": "Dairy Products",
      "Description": "Cheeses"
    },
    "ProductID": 59,
    "ProductName": "Raclette Courdavault",
    "Cost": 55.0,
    "Stock": 79,
    "Discontinued": false,
    "CategoryID": 4
  },
  {
    "Category": {
      "CategoryID": 7,
      "CategoryName": "Produce",
      "Description": "Dried fruit and bean curd"
    },
    "ProductID": 51,
    "ProductName": "Manjimup Dried Apples",
    "Cost": 53.0,
    "Stock": 20,
    "Discontinued": false,
    "CategoryID": 7
  },
  {
    "Category": {
      "CategoryID": 3,
      "CategoryName": "Confections",
      "Description": "Desserts, candies, and sweet breads"
    },
    "ProductID": 62,
    "ProductName": "Tarte au sucre",
    "Cost": 49.3,
    "Stock": 17,
    "Discontinued": false,
    "CategoryID": 3
  },
  {
    "Category": {
      "CategoryID": 1,
      "CategoryName": "Beverages",
      "Description": "Soft drinks, coffees, teas, beers, and ales"
    },
    "ProductID": 43,
    "ProductName": "Ipoh Coffee",
    "Cost": 46.0,
    "Stock": 17,
    "Discontinued": false,
    "CategoryID": 1
  },
  {
    "Category": {
      "CategoryID": 3,
      "CategoryName": "Confections",
      "Description": "Desserts, candies, and sweet breads"
    },
    "ProductID": 27,
    "ProductName": "Schoggi Schokolade",
    "Cost": 43.9,
    "Stock": 49,
    "Discontinued": false,
    "CategoryID": 3
  },
  {
    "Category": {
      "CategoryID": 2,
      "CategoryName": "Condiments",
      "Description": "Sweet and savory sauces, relishes, spreads, and seasonings"
    },
    "ProductID": 63,
    "ProductName": "Vegie-spread",
    "Cost": 43.9,
    "Stock": 24,
    "Discontinued": false,
    "CategoryID": 2
  },
  {
    "Category": {
      "CategoryID": 2,
      "CategoryName": "Condiments",
      "Description": "Sweet and savory sauces, relishes, spreads, and seasonings"
    },
    "ProductID": 8,
    "ProductName": "Northwoods Cranberry Sauce",
    "Cost": 40.0,
    "Stock": 6,
    "Discontinued": false,
    "CategoryID": 2
  },
  {
    "Category": {
      "CategoryID": 4,
      "CategoryName": "Dairy Products",
      "Description": "Cheeses"
    },
    "ProductID": 12,
    "ProductName": "Queso Manchego La Pastora",
    "Cost": 38.0,
    "Stock": 86,
    "Discontinued": false,
    "CategoryID": 4
  },
  {
    "Category": {
      "CategoryID": 5,
      "CategoryName": "Grains/Cereals",
      "Description": "Breads, crackers, pasta, and cereal"
    },
    "ProductID": 56,
    "ProductName": "Gnocchi di nonna Alice",
    "Cost": 38.0,
    "Stock": 21,
    "Discontinued": false,
    "CategoryID": 5
  },
  {
    "Category": {
      "CategoryID": 4,
      "CategoryName": "Dairy Products",
      "Description": "Cheeses"
    },
    "ProductID": 69,
    "ProductName": "Gudbrandsdalsost",
    "Cost": 36.0,
    "Stock": 26,
    "Discontinued": false,
    "CategoryID": 4
  },
  {
    "Category": {
      "CategoryID": 4,
      "CategoryName": "Dairy Products",
      "Description": "Cheeses"
    },
    "ProductID": 72,
    "ProductName": "Mozzarella di Giovanni",
    "Cost": 34.8,
    "Stock": 14,
    "Discontinued": false,
    "CategoryID": 4
  },
  {
    "Category": {
      "CategoryID": 4,
      "CategoryName": "Dairy Products",
      "Description": "Cheeses"
    },
    "ProductID": 60,
    "ProductName": "Camembert Pierrot",
    "Cost": 34.0,
    "Stock": 19,
    "Discontinued": false,
    "CategoryID": 4
  },
  {
    "Category": {
      "CategoryID": 5,
      "CategoryName": "Grains/Cereals",
      "Description": "Breads, crackers, pasta, and cereal"
    },
    "ProductID": 64,
    "ProductName": "Wimmers gute Semmelknödel",
    "Cost": 33.25,
    "Stock": 22,
    "Discontinued": false,
    "CategoryID": 5
  },
  {
    "Category": {
      "CategoryID": 4,
      "CategoryName": "Dairy Products",
      "Description": "Cheeses"
    },
    "ProductID": 32,
    "ProductName": "Mascarpone Fabioli",
    "Cost": 32.0,
    "Stock": 9,
    "Discontinued": false,
    "CategoryID": 4
  },
  {
    "Category": {
      "CategoryID": 3,
      "CategoryName": "Confections",
      "Description": "Desserts, candies, and sweet breads"
    },
    "ProductID": 26,
    "ProductName": "Gumbär Gummibärchen",
    "Cost": 31.23,
    "Stock": 15,
    "Discontinued": false,
    "CategoryID": 3
  },
  {
    "Category": {
      "CategoryID": 8,
      "CategoryName": "Seafood",
      "Description": "Seaweed and fish"
    },
    "ProductID": 10,
    "ProductName": "Ikura",
    "Cost": 31.0,
    "Stock": 31,
    "Discontinued": false,
    "CategoryID": 8
  },
  {
    "Category": {
      "CategoryID": 7,
      "CategoryName": "Produce",
      "Description": "Dried fruit and bean curd"
    },
    "ProductID": 7,
    "ProductName": "Uncle Bob's Organic Dried Pears",
    "Cost": 30.0,
    "Stock": 15,
    "Discontinued": false,
    "CategoryID": 7
  },
  {
    "Category": {
      "CategoryID": 2,
      "CategoryName": "Condiments",
      "Description": "Sweet and savory sauces, relishes, spreads, and seasonings"
    },
    "ProductID": 61,
    "ProductName": "Sirop d'érable",
    "Cost": 28.5,
    "Stock": 113,
    "Discontinued": false,
    "CategoryID": 2
  },
  {
    "Category": {
      "CategoryID": 8,
      "CategoryName": "Seafood",
      "Description": "Seaweed and fish"
    },
    "ProductID": 37,
    "ProductName": "Gravad lax",
    "Cost": 26.0,
    "Stock": 11,
    "Discontinued": false,
    "CategoryID": 8
  },
  {
    "Category": {
      "CategoryID": 8,
      "CategoryName": "Seafood",
      "Description": "Seaweed and fish"
    },
    "ProductID": 30,
    "ProductName": "Nord-Ost Matjeshering",
    "Cost": 25.89,
    "Stock": 10,
    "Discontinued": false,
    "CategoryID": 8
  },
  {
    "Category": {
      "CategoryID": 2,
      "CategoryName": "Condiments",
      "Description": "Sweet and savory sauces, relishes, spreads, and seasonings"
    },
    "ProductID": 6,
    "ProductName": "Grandma's Boysenberry Spread",
    "Cost": 25.0,
    "Stock": 120,
    "Discontinued": false,
    "CategoryID": 2
  },
  {
    "Category": {
      "CategoryID": 6,
      "CategoryName": "Meat/Poultry",
      "Description": "Prepared meats"
    },
    "ProductID": 55,
    "ProductName": "Pâté chinois",
    "Cost": 24.0,
    "Stock": 115,
    "Discontinued": false,
    "CategoryID": 6
  },
  {
    "Category": {
      "CategoryID": 7,
      "CategoryName": "Produce",
      "Description": "Dried fruit and bean curd"
    },
    "ProductID": 14,
    "ProductName": "Tofu",
    "Cost": 23.25,
    "Stock": 35,
    "Discontinued": false,
    "CategoryID": 7
  },
  {
    "Category": {
      "CategoryID": 2,
      "CategoryName": "Condiments",
      "Description": "Sweet and savory sauces, relishes, spreads, and seasonings"
    },
    "ProductID": 4,
    "ProductName": "Chef Anton's Cajun Seasoning",
    "Cost": 22.0,
    "Stock": 53,
    "Discontinued": false,
    "CategoryID": 2
  },
  {
    "Category": {
      "CategoryID": 4,
      "CategoryName": "Dairy Products",
      "Description": "Cheeses"
    },
    "ProductID": 71,
    "ProductName": "Flotemysost",
    "Cost": 21.5,
    "Stock": 26,
    "Discontinued": false,
    "CategoryID": 4
  },
  {
    "Category": {
      "CategoryID": 2,
      "CategoryName": "Condiments",
      "Description": "Sweet and savory sauces, relishes, spreads, and seasonings"
    },
    "ProductID": 65,
    "ProductName": "Louisiana Fiery Hot Pepper Sauce",
    "Cost": 21.05,
    "Stock": 76,
    "Discontinued": false,
    "CategoryID": 2
  },
  {
    "Category": {
      "CategoryID": 4,
      "CategoryName": "Dairy Products",
      "Description": "Cheeses"
    },
    "ProductID": 11,
    "ProductName": "Queso Cabrales",
    "Cost": 21.0,
    "Stock": 22,
    "Discontinued": false,
    "CategoryID": 4
  },
  {
    "Category": {
      "CategoryID": 5,
      "CategoryName": "Grains/Cereals",
      "Description": "Breads, crackers, pasta, and cereal"
    },
    "ProductID": 22,
    "ProductName": "Gustaf's Knäckebröd",
    "Cost": 21.0,
    "Stock": 104,
    "Discontinued": false,
    "CategoryID": 5
  },
  {
    "Category": {
      "CategoryID": 3,
      "CategoryName": "Confections",
      "Description": "Desserts, candies, and sweet breads"
    },
    "ProductID": 49,
    "ProductName": "Maxilaku",
    "Cost": 20.0,
    "Stock": 10,
    "Discontinued": false,
    "CategoryID": 3
  },
  {
    "Category": {
      "CategoryID": 5,
      "CategoryName": "Grains/Cereals",
      "Description": "Breads, crackers, pasta, and cereal"
    },
    "ProductID": 57,
    "ProductName": "Ravioli Angelo",
    "Cost": 19.5,
    "Stock": 36,
    "Discontinued": false,
    "CategoryID": 5
  },
  {
    "Category": {
      "CategoryID": 2,
      "CategoryName": "Condiments",
      "Description": "Sweet and savory sauces, relishes, spreads, and seasonings"
    },
    "ProductID": 44,
    "ProductName": "Gula Malacca",
    "Cost": 19.45,
    "Stock": 27,
    "Discontinued": false,
    "CategoryID": 2
  },
  {
    "Category": {
      "CategoryID": 1,
      "CategoryName": "Beverages",
      "Description": "Soft drinks, coffees, teas, beers, and ales"
    },
    "ProductID": 2,
    "ProductName": "Chang",
    "Cost": 19.0,
    "Stock": 17,
    "Discontinued": false,
    "CategoryID": 1
  },
  {
    "Category": {
      "CategoryID": 8,
      "CategoryName": "Seafood",
      "Description": "Seaweed and fish"
    },
    "ProductID": 36,
    "ProductName": "Inlagd Sill",
    "Cost": 19.0,
    "Stock": 112,
    "Discontinued": false,
    "CategoryID": 8
  },
  {
    "Category": {
      "CategoryID": 8,
      "CategoryName": "Seafood",
      "Description": "Seaweed and fish"
    },
    "ProductID": 40,
    "ProductName": "Boston Crab Meat",
    "Cost": 18.4,
    "Stock": 123,
    "Discontinued": false,
    "CategoryID": 8
  },
  {
    "Category": {
      "CategoryID": 1,
      "CategoryName": "Beverages",
      "Description": "Soft drinks, coffees, teas, beers, and ales"
    },
    "ProductID": 1,
    "ProductName": "Chai",
    "Cost": 18.0,
    "Stock": 39,
    "Discontinued": false,
    "CategoryID": 1
  },
  {
    "Category": {
      "CategoryID": 1,
      "CategoryName": "Beverages",
      "Description": "Soft drinks, coffees, teas, beers, and ales"
    },
    "ProductID": 35,
    "ProductName": "Steeleye Stout",
    "Cost": 18.0,
    "Stock": 20,
    "Discontinued": false,
    "CategoryID": 1
  },
  {
    "Category": {
      "CategoryID": 1,
      "CategoryName": "Beverages",
      "Description": "Soft drinks, coffees, teas, beers, and ales"
    },
    "ProductID": 39,
    "ProductName": "Chartreuse verte",
    "Cost": 18.0,
    "Stock": 69,
    "Discontinued": false,
    "CategoryID": 1
  },
  {
    "Category": {
      "CategoryID": 1,
      "CategoryName": "Beverages",
      "Description": "Soft drinks, coffees, teas, beers, and ales"
    },
    "ProductID": 76,
    "ProductName": "Lakkalikööri",
    "Cost": 18.0,
    "Stock": 57,
    "Discontinued": false,
    "CategoryID": 1
  },
  {
    "Category": {
      "CategoryID": 3,
      "CategoryName": "Confections",
      "Description": "Desserts, candies, and sweet breads"
    },
    "ProductID": 16,
    "ProductName": "Pavlova",
    "Cost": 17.45,
    "Stock": 29,
    "Discontinued": false,
    "CategoryID": 3
  },
  {
    "Category": {
      "CategoryID": 2,
      "CategoryName": "Condiments",
      "Description": "Sweet and savory sauces, relishes, spreads, and seasonings"
    },
    "ProductID": 66,
    "ProductName": "Louisiana Hot Spiced Okra",
    "Cost": 17.0,
    "Stock": 4,
    "Discontinued": false,
    "CategoryID": 2
  },
  {
    "Category": {
      "CategoryID": 3,
      "CategoryName": "Confections",
      "Description": "Desserts, candies, and sweet breads"
    },
    "ProductID": 50,
    "ProductName": "Valkoinen suklaa",
    "Cost": 16.25,
    "Stock": 65,
    "Discontinued": false,
    "CategoryID": 3
  },
  {
    "Category": {
      "CategoryID": 2,
      "CategoryName": "Condiments",
      "Description": "Sweet and savory sauces, relishes, spreads, and seasonings"
    },
    "ProductID": 15,
    "ProductName": "Genen Shouyu",
    "Cost": 15.5,
    "Stock": 39,
    "Discontinued": false,
    "CategoryID": 2
  },
  {
    "Category": {
      "CategoryID": 1,
      "CategoryName": "Beverages",
      "Description": "Soft drinks, coffees, teas, beers, and ales"
    },
    "ProductID": 70,
    "ProductName": "Outback Lager",
    "Cost": 15.0,
    "Stock": 15,
    "Discontinued": false,
    "CategoryID": 1
  },
  {
    "Category": {
      "CategoryID": 8,
      "CategoryName": "Seafood",
      "Description": "Seaweed and fish"
    },
    "ProductID": 73,
    "ProductName": "Röd Kaviar",
    "Cost": 15.0,
    "Stock": 101,
    "Discontinued": false,
    "CategoryID": 8
  },
  {
    "Category": {
      "CategoryID": 3,
      "CategoryName": "Confections",
      "Description": "Desserts, candies, and sweet breads"
    },
    "ProductID": 25,
    "ProductName": "NuNuCa Nuß-Nougat-Creme",
    "Cost": 14.0,
    "Stock": 76,
    "Discontinued": false,
    "CategoryID": 3
  },
  {
    "Category": {
      "CategoryID": 1,
      "CategoryName": "Beverages",
      "Description": "Soft drinks, coffees, teas, beers, and ales"
    },
    "ProductID": 34,
    "ProductName": "Sasquatch Ale",
    "Cost": 14.0,
    "Stock": 111,
    "Discontinued": false,
    "CategoryID": 1
  },
  {
    "Category": {
      "CategoryID": 1,
      "CategoryName": "Beverages",
      "Description": "Soft drinks, coffees, teas, beers, and ales"
    },
    "ProductID": 67,
    "ProductName": "Laughing Lumberjack Lager",
    "Cost": 14.0,
    "Stock": 52,
    "Discontinued": false,
    "CategoryID": 1
  },
  {
    "Category": {
      "CategoryID": 8,
      "CategoryName": "Seafood",
      "Description": "Seaweed and fish"
    },
    "ProductID": 58,
    "ProductName": "Escargots de Bourgogne",
    "Cost": 13.25,
    "Stock": 62,
    "Discontinued": false,
    "CategoryID": 8
  },
  {
    "Category": {
      "CategoryID": 2,
      "CategoryName": "Condiments",
      "Description": "Sweet and savory sauces, relishes, spreads, and seasonings"
    },
    "ProductID": 77,
    "ProductName": "Original Frankfurter grüne Soße",
    "Cost": 13.0,
    "Stock": 32,
    "Discontinued": false,
    "CategoryID": 2
  },
  {
    "Category": {
      "CategoryID": 3,
      "CategoryName": "Confections",
      "Description": "Desserts, candies, and sweet breads"
    },
    "ProductID": 48,
    "ProductName": "Chocolade",
    "Cost": 12.75,
    "Stock": 15,
    "Discontinued": false,
    "CategoryID": 3
  },
  {
    "Category": {
      "CategoryID": 4,
      "CategoryName": "Dairy Products",
      "Description": "Cheeses"
    },
    "ProductID": 31,
    "ProductName": "Gorgonzola Telino",
    "Cost": 12.5,
    "Stock": 0,
    "Discontinued": false,
    "CategoryID": 4
  },
  {
    "Category": {
      "CategoryID": 3,
      "CategoryName": "Confections",
      "Description": "Desserts, candies, and sweet breads"
    },
    "ProductID": 68,
    "ProductName": "Scottish Longbreads",
    "Cost": 12.5,
    "Stock": 6,
    "Discontinued": false,
    "CategoryID": 3
  },
  {
    "Category": {
      "CategoryID": 8,
      "CategoryName": "Seafood",
      "Description": "Seaweed and fish"
    },
    "ProductID": 46,
    "ProductName": "Spegesild",
    "Cost": 12.0,
    "Stock": 95,
    "Discontinued": false,
    "CategoryID": 8
  },
  {
    "Category": {
      "CategoryID": 2,
      "CategoryName": "Condiments",
      "Description": "Sweet and savory sauces, relishes, spreads, and seasonings"
    },
    "ProductID": 3,
    "ProductName": "Aniseed Syrup",
    "Cost": 10.0,
    "Stock": 13,
    "Discontinued": false,
    "CategoryID": 2
  },
  {
    "Category": {
      "CategoryID": 3,
      "CategoryName": "Confections",
      "Description": "Desserts, candies, and sweet breads"
    },
    "ProductID": 21,
    "ProductName": "Sir Rodney's Scones",
    "Cost": 10.0,
    "Stock": 3,
    "Discontinued": false,
    "CategoryID": 3
  },
  {
    "Category": {
      "CategoryID": 7,
      "CategoryName": "Produce",
      "Description": "Dried fruit and bean curd"
    },
    "ProductID": 74,
    "ProductName": "Longlife Tofu",
    "Cost": 10.0,
    "Stock": 4,
    "Discontinued": false,
    "CategoryID": 7
  },
  {
    "Category": {
      "CategoryID": 8,
      "CategoryName": "Seafood",
      "Description": "Seaweed and fish"
    },
    "ProductID": 41,
    "ProductName": "Jack's New England Clam Chowder",
    "Cost": 9.65,
    "Stock": 85,
    "Discontinued": false,
    "CategoryID": 8
  },
  {
    "Category": {
      "CategoryID": 8,
      "CategoryName": "Seafood",
      "Description": "Seaweed and fish"
    },
    "ProductID": 45,
    "ProductName": "Rogede sild",
    "Cost": 9.5,
    "Stock": 5,
    "Discontinued": false,
    "CategoryID": 8
  },
  {
    "Category": {
      "CategoryID": 3,
      "CategoryName": "Confections",
      "Description": "Desserts, candies, and sweet breads"
    },
    "ProductID": 47,
    "ProductName": "Zaanse koeken",
    "Cost": 9.5,
    "Stock": 36,
    "Discontinued": false,
    "CategoryID": 3
  },
  {
    "Category": {
      "CategoryID": 3,
      "CategoryName": "Confections",
      "Description": "Desserts, candies, and sweet breads"
    },
    "ProductID": 19,
    "ProductName": "Teatime Chocolate Biscuits",
    "Cost": 9.2,
    "Stock": 25,
    "Discontinued": false,
    "CategoryID": 3
  },
  {
    "Category": {
      "CategoryID": 5,
      "CategoryName": "Grains/Cereals",
      "Description": "Breads, crackers, pasta, and cereal"
    },
    "ProductID": 23,
    "ProductName": "Tunnbröd",
    "Cost": 9.0,
    "Stock": 61,
    "Discontinued": false,
    "CategoryID": 5
  },
  {
    "Category": {
      "CategoryID": 1,
      "CategoryName": "Beverages",
      "Description": "Soft drinks, coffees, teas, beers, and ales"
    },
    "ProductID": 75,
    "ProductName": "Rhönbräu Klosterbier",
    "Cost": 7.75,
    "Stock": 125,
    "Discontinued": false,
    "CategoryID": 1
  },
  {
    "Category": {
      "CategoryID": 6,
      "CategoryName": "Meat/Poultry",
      "Description": "Prepared meats"
    },
    "ProductID": 54,
    "ProductName": "Tourtière",
    "Cost": 7.45,
    "Stock": 21,
    "Discontinued": false,
    "CategoryID": 6
  },
  {
    "Category": {
      "CategoryID": 5,
      "CategoryName": "Grains/Cereals",
      "Description": "Breads, crackers, pasta, and cereal"
    },
    "ProductID": 52,
    "ProductName": "Filo Mix",
    "Cost": 7.0,
    "Stock": 38,
    "Discontinued": false,
    "CategoryID": 5
  },
  {
    "Category": {
      "CategoryID": 8,
      "CategoryName": "Seafood",
      "Description": "Seaweed and fish"
    },
    "ProductID": 13,
    "ProductName": "Konbu",
    "Cost": 6.0,
    "Stock": 24,
    "Discontinued": false,
    "CategoryID": 8
  },
  {
    "Category": {
      "CategoryID": 4,
      "CategoryName": "Dairy Products",
      "Description": "Cheeses"
    },
    "ProductID": 33,
    "ProductName": "Geitost",
    "Cost": 2.5,
    "Stock": 112,
    "Discontinued": false,
    "CategoryID": 4
  }
]
